credit_pdfextract/PDFExtractor.py
credit_pdfextract/__init__.py
credit_pdfextract-0.2.dist-info/METADATA
credit_pdfextract-0.2.dist-info/WHEEL
credit_pdfextract-0.2.dist-info/top_level.txt
credit_pdfextract-0.2.dist-info/RECORD
