Metadata-Version: 2.1
Name: credit_pdfextract
Version: 0.2
Summary: a pdf extract library
Author: Cheng kang
Requires-Dist: pdfplumber
Requires-Dist: pandas
